{"abstract":[{"text":"Inherited from ","type":"text"},{"type":"codeVoice","code":"View.confirmationDialog(_:isPresented:titleVisibility:presenting:actions:message:)"},{"text":".","type":"text"}],"hierarchy":{"paths":[["doc:\/\/com.swift-man.LaunchingView\/documentation\/LaunchingView","doc:\/\/com.swift-man.LaunchingView\/documentation\/LaunchingView\/LaunchingView"]]},"primaryContentSections":[{"kind":"declarations","declarations":[{"languages":["swift"],"platforms":["macOS"],"tokens":[{"text":"nonisolated","kind":"attribute"},{"text":" ","kind":"text"},{"text":"func","kind":"keyword"},{"text":" ","kind":"text"},{"text":"confirmationDialog","kind":"identifier"},{"text":"<","kind":"text"},{"text":"S","kind":"genericParameter"},{"text":", ","kind":"text"},{"text":"A","kind":"genericParameter"},{"text":", ","kind":"text"},{"text":"M","kind":"genericParameter"},{"text":", ","kind":"text"},{"text":"T","kind":"genericParameter"},{"text":">(","kind":"text"},{"text":"_","kind":"externalParam"},{"text":" ","kind":"text"},{"text":"title","kind":"internalParam"},{"text":": ","kind":"text"},{"text":"S","kind":"typeIdentifier"},{"text":", ","kind":"text"},{"text":"isPresented","kind":"externalParam"},{"text":": ","kind":"text"},{"preciseIdentifier":"s:7SwiftUI7BindingV","text":"Binding","kind":"typeIdentifier"},{"text":"<","kind":"text"},{"preciseIdentifier":"s:Sb","text":"Bool","kind":"typeIdentifier"},{"text":">, ","kind":"text"},{"text":"titleVisibility","kind":"externalParam"},{"text":": ","kind":"text"},{"preciseIdentifier":"s:7SwiftUI10VisibilityO","text":"Visibility","kind":"typeIdentifier"},{"text":" = .automatic, ","kind":"text"},{"text":"presenting","kind":"externalParam"},{"text":" ","kind":"text"},{"text":"data","kind":"internalParam"},{"text":": ","kind":"text"},{"text":"T","kind":"typeIdentifier"},{"text":"?, ","kind":"text"},{"text":"@","kind":"attribute"},{"preciseIdentifier":"s:7SwiftUI11ViewBuilderV","text":"ViewBuilder","kind":"attribute"},{"text":" ","kind":"text"},{"text":"actions","kind":"externalParam"},{"text":": (","kind":"text"},{"text":"T","kind":"typeIdentifier"},{"text":") -> ","kind":"text"},{"text":"A","kind":"typeIdentifier"},{"text":", ","kind":"text"},{"text":"@","kind":"attribute"},{"preciseIdentifier":"s:7SwiftUI11ViewBuilderV","text":"ViewBuilder","kind":"attribute"},{"text":" ","kind":"text"},{"text":"message","kind":"externalParam"},{"text":": (","kind":"text"},{"text":"T","kind":"typeIdentifier"},{"text":") -> ","kind":"text"},{"text":"M","kind":"typeIdentifier"},{"text":") -> ","kind":"text"},{"text":"some","kind":"keyword"},{"text":" ","kind":"text"},{"preciseIdentifier":"s:7SwiftUI4ViewP","text":"View","kind":"typeIdentifier"},{"text":" ","kind":"text"},{"text":"where","kind":"keyword"},{"text":" ","kind":"text"},{"text":"S","kind":"typeIdentifier"},{"text":" : ","kind":"text"},{"preciseIdentifier":"s:Sy","text":"StringProtocol","kind":"typeIdentifier"},{"text":", ","kind":"text"},{"text":"A","kind":"typeIdentifier"},{"text":" : ","kind":"text"},{"preciseIdentifier":"s:7SwiftUI4ViewP","text":"View","kind":"typeIdentifier"},{"text":", ","kind":"text"},{"text":"M","kind":"typeIdentifier"},{"text":" : ","kind":"text"},{"preciseIdentifier":"s:7SwiftUI4ViewP","text":"View","kind":"typeIdentifier"},{"text":"\n","kind":"text"}]}]}],"variants":[{"traits":[{"interfaceLanguage":"swift"}],"paths":["\/documentation\/launchingview\/launchingview\/confirmationdialog(_:ispresented:titlevisibility:presenting:actions:message:)-5rm06"]}],"sections":[],"schemaVersion":{"minor":3,"patch":0,"major":0},"identifier":{"url":"doc:\/\/com.swift-man.LaunchingView\/documentation\/LaunchingView\/LaunchingView\/confirmationDialog(_:isPresented:titleVisibility:presenting:actions:message:)-5rm06","interfaceLanguage":"swift"},"kind":"symbol","metadata":{"symbolKind":"method","roleHeading":"Instance Method","modules":[{"relatedModules":["SwiftUICore"],"name":"LaunchingView"}],"platforms":[{"deprecated":false,"name":"iOS","beta":false,"unavailable":false,"introducedAt":"15.0"},{"deprecated":false,"name":"macOS","beta":false,"unavailable":false,"introducedAt":"12.0"},{"deprecated":false,"name":"tvOS","beta":false,"unavailable":false,"introducedAt":"15.0"},{"deprecated":false,"name":"watchOS","beta":false,"unavailable":false,"introducedAt":"8.0"}],"title":"confirmationDialog(_:isPresented:titleVisibility:presenting:actions:message:)","fragments":[{"text":"func","kind":"keyword"},{"text":" ","kind":"text"},{"text":"confirmationDialog","kind":"identifier"},{"text":"<","kind":"text"},{"text":"S","kind":"genericParameter"},{"text":", ","kind":"text"},{"text":"A","kind":"genericParameter"},{"text":", ","kind":"text"},{"text":"M","kind":"genericParameter"},{"text":", ","kind":"text"},{"text":"T","kind":"genericParameter"},{"text":">(","kind":"text"},{"text":"S","kind":"typeIdentifier"},{"text":", ","kind":"text"},{"text":"isPresented","kind":"externalParam"},{"text":": ","kind":"text"},{"preciseIdentifier":"s:7SwiftUI7BindingV","text":"Binding","kind":"typeIdentifier"},{"text":"<","kind":"text"},{"preciseIdentifier":"s:Sb","text":"Bool","kind":"typeIdentifier"},{"text":">, ","kind":"text"},{"text":"titleVisibility","kind":"externalParam"},{"text":": ","kind":"text"},{"preciseIdentifier":"s:7SwiftUI10VisibilityO","text":"Visibility","kind":"typeIdentifier"},{"text":", ","kind":"text"},{"text":"presenting","kind":"externalParam"},{"text":": ","kind":"text"},{"text":"T","kind":"typeIdentifier"},{"text":"?, ","kind":"text"},{"text":"actions","kind":"externalParam"},{"text":": (","kind":"text"},{"text":"T","kind":"typeIdentifier"},{"text":") -> ","kind":"text"},{"text":"A","kind":"typeIdentifier"},{"text":", ","kind":"text"},{"text":"message","kind":"externalParam"},{"text":": (","kind":"text"},{"text":"T","kind":"typeIdentifier"},{"text":") -> ","kind":"text"},{"text":"M","kind":"typeIdentifier"},{"text":") -> ","kind":"text"},{"text":"some","kind":"keyword"},{"text":" ","kind":"text"},{"preciseIdentifier":"s:7SwiftUI4ViewP","text":"View","kind":"typeIdentifier"}],"extendedModule":"SwiftUICore","role":"symbol","externalID":"s:7SwiftUI4ViewPAAE18confirmationDialog_11isPresented15titleVisibility10presenting7actions7messageQrqd___AA7BindingVySbGAA0I0Oqd_2_Sgqd_0_qd_2_XEqd_1_qd_2_XEtSyRd__AaBRd_0_AaBRd_1_r2_lF::SYNTHESIZED::s:13LaunchingViewAAV"},"references":{"doc://com.swift-man.LaunchingView/documentation/LaunchingView":{"url":"\/documentation\/launchingview","title":"LaunchingView","role":"collection","kind":"symbol","type":"topic","identifier":"doc:\/\/com.swift-man.LaunchingView\/documentation\/LaunchingView","abstract":[{"text":"This is a SwiftUI view based on ","type":"text"},{"identifier":"https:\/\/github.com\/pointfreeco\/swift-composable-architecture","isActive":true,"type":"reference"},{"type":"text","text":"."}]},"doc://com.swift-man.LaunchingView/documentation/LaunchingView/LaunchingView/confirmationDialog(_:isPresented:titleVisibility:presenting:actions:message:)-5rm06":{"abstract":[],"type":"topic","identifier":"doc:\/\/com.swift-man.LaunchingView\/documentation\/LaunchingView\/LaunchingView\/confirmationDialog(_:isPresented:titleVisibility:presenting:actions:message:)-5rm06","url":"\/documentation\/launchingview\/launchingview\/confirmationdialog(_:ispresented:titlevisibility:presenting:actions:message:)-5rm06","kind":"symbol","role":"symbol","title":"confirmationDialog(_:isPresented:titleVisibility:presenting:actions:message:)","fragments":[{"kind":"keyword","text":"func"},{"kind":"text","text":" "},{"kind":"identifier","text":"confirmationDialog"},{"kind":"text","text":"<"},{"kind":"genericParameter","text":"S"},{"kind":"text","text":", "},{"kind":"genericParameter","text":"A"},{"kind":"text","text":", "},{"kind":"genericParameter","text":"M"},{"kind":"text","text":", "},{"kind":"genericParameter","text":"T"},{"text":">(","kind":"text"},{"text":"S","kind":"typeIdentifier"},{"text":", ","kind":"text"},{"text":"isPresented","kind":"externalParam"},{"text":": ","kind":"text"},{"text":"Binding","preciseIdentifier":"s:7SwiftUI7BindingV","kind":"typeIdentifier"},{"text":"<","kind":"text"},{"text":"Bool","preciseIdentifier":"s:Sb","kind":"typeIdentifier"},{"text":">, ","kind":"text"},{"text":"titleVisibility","kind":"externalParam"},{"text":": ","kind":"text"},{"text":"Visibility","preciseIdentifier":"s:7SwiftUI10VisibilityO","kind":"typeIdentifier"},{"text":", ","kind":"text"},{"text":"presenting","kind":"externalParam"},{"text":": ","kind":"text"},{"text":"T","kind":"typeIdentifier"},{"text":"?, ","kind":"text"},{"text":"actions","kind":"externalParam"},{"text":": (","kind":"text"},{"text":"T","kind":"typeIdentifier"},{"text":") -> ","kind":"text"},{"text":"A","kind":"typeIdentifier"},{"text":", ","kind":"text"},{"text":"message","kind":"externalParam"},{"text":": (","kind":"text"},{"text":"T","kind":"typeIdentifier"},{"text":") -> ","kind":"text"},{"text":"M","kind":"typeIdentifier"},{"text":") -> ","kind":"text"},{"text":"some","kind":"keyword"},{"text":" ","kind":"text"},{"text":"View","preciseIdentifier":"s:7SwiftUI4ViewP","kind":"typeIdentifier"}]},"https://github.com/pointfreeco/swift-composable-architecture":{"url":"https:\/\/github.com\/pointfreeco\/swift-composable-architecture","titleInlineContent":[{"type":"text","text":"The Composable Architecture"}],"identifier":"https:\/\/github.com\/pointfreeco\/swift-composable-architecture","title":"The Composable Architecture","type":"link"},"doc://com.swift-man.LaunchingView/documentation/LaunchingView/LaunchingView":{"navigatorTitle":[{"kind":"identifier","text":"LaunchingView"}],"title":"LaunchingView","type":"topic","abstract":[{"text":"LaunchingView는 App 구동전 스플레시 역할을 합니다.","type":"text"}],"kind":"symbol","role":"symbol","identifier":"doc:\/\/com.swift-man.LaunchingView\/documentation\/LaunchingView\/LaunchingView","url":"\/documentation\/launchingview\/launchingview","fragments":[{"kind":"keyword","text":"struct"},{"kind":"text","text":" "},{"kind":"identifier","text":"LaunchingView"}]}}}